mysql_migrator/__init__.py
mysql_migrator/__main__.py
mysql_migrator/cli.py
mysql_migrator/migrator.py
rethinkport-1.0.3.dist-info/licenses/LICENSE
rethinkport-1.0.3.dist-info/METADATA
rethinkport-1.0.3.dist-info/WHEEL
rethinkport-1.0.3.dist-info/entry_points.txt
rethinkport-1.0.3.dist-info/top_level.txt
rethinkport-1.0.3.dist-info/RECORD
