Metadata-Version: 2.4
Name: rethinkport
Version: 1.0.3
Summary: Port your RethinkDB data to MySQL
Home-page: https://github.com/aoamusat/rethinkport
Author: Akeem Amusat
Author-email: Akeem Amusat <hello@a4m.dev>
License: MIT
Project-URL: Homepage, https://github.com/aoamusat/rethinkport
Project-URL: Bug Reports, https://github.com/aoamusat/rethinkport/issues
Project-URL: Source, https://github.com/aoamusat/rethinkport
Project-URL: Documentation, https://github.com/aoamusat/rethinkport#readme
Keywords: rethinkdb,mysql,migration,database,port,converter
Classifier: Development Status :: 4 - Beta
Classifier: Intended Audience :: Developers
Classifier: License :: OSI Approved :: MIT License
Classifier: Operating System :: OS Independent
Classifier: Programming Language :: Python :: 3
Classifier: Programming Language :: Python :: 3.9
Classifier: Programming Language :: Python :: 3.10
Classifier: Programming Language :: Python :: 3.11
Classifier: Programming Language :: Python :: 3.12
Classifier: Topic :: Database
Classifier: Topic :: Software Development :: Libraries :: Python Modules
Classifier: Topic :: Utilities
Requires-Python: >=3.9
License-File: LICENSE
Requires-Dist: pymysql>=1.0.2
Requires-Dist: click>=8.0.0
Requires-Dist: tqdm>=4.64.0
Requires-Dist: colorama>=0.4.4
Dynamic: author
Dynamic: home-page
Dynamic: license-file
Dynamic: requires-python
